LICENSE
README.md
pyproject.toml
setup.py
pkuiaaa/__init__.py
pkuiaaa/session.py
pkuiaaa.egg-info/PKG-INFO
pkuiaaa.egg-info/SOURCES.txt
pkuiaaa.egg-info/dependency_links.txt
pkuiaaa.egg-info/entry_points.txt
pkuiaaa.egg-info/requires.txt
pkuiaaa.egg-info/top_level.txt