Metadata-Version: 2.1
Name: pkuiaaa
Version: 0.1.1
Summary: It returns you a logged in requests session
Author: xiaotianxt
Author-email: xiaotianxt <tianyp@pku.edu.cn>
License:                     GNU GENERAL PUBLIC LICENSE
Project-URL: Homepage, https://github.com/xiaotianxt/pkuiaaa
Keywords: pku,iaaa,oauth
Classifier: Programming Language :: Python
Classifier: Programming Language :: Python :: 3
Requires: requests
Requires-Python: >=3.6
Provides-Extra: dev
License-File: LICENSE
